poja/__init__.py
poja/__main__.py
poja/core.py
poja/version.py
poja/database/__init__.py
poja/genclients/__init__.py
poja/mygit/__init__.py
poja/myos/__init__.py
poja/myrich/__init__.py
poja/sed/__init__.py
poja/sentry/__init__.py
poja/sonar/__init__.py
poja/vpcscoped/__init__.py
dname_code_gen-13.1.4.dist-info/LICENSE
dname_code_gen-13.1.4.dist-info/METADATA
dname_code_gen-13.1.4.dist-info/WHEEL
dname_code_gen-13.1.4.dist-info/top_level.txt
dname_code_gen-13.1.4.dist-info/RECORD
