Metadata-Version: 2.1
Name: dname-code-gen
Version: 13.1.4
Summary: Serverless Java(+Postgres or SQLite) hosted on Github+AWS
Home-page: https://github.com/Daris02/code-gen-cli
Author: Daris02
Author-email: hei.raymond.2@gmail.com
License-File: LICENSE
Requires-Dist: pyyaml
Requires-Dist: fire
Requires-Dist: gitpython
Requires-Dist: rich
